t7pro/__init__.py
t7pro/constants.py
t7pro/t7pro_form.py
t7pro/t7pro_gui.py
t7pro/version.py
t7pro-0.1.3.data/data/share/applications/t7pro.desktop
t7pro-0.1.3.data/data/share/icons/hicolor/scalable/apps/t7pro.svg
t7pro-0.1.3.data/scripts/t7pro-gui
t7pro-0.1.3.dist-info/LICENSE.txt
t7pro-0.1.3.dist-info/METADATA
t7pro-0.1.3.dist-info/WHEEL
t7pro-0.1.3.dist-info/top_level.txt
t7pro-0.1.3.dist-info/RECORD
