Metadata-Version: 2.1
Name: t7pro
Version: 0.1.3
Summary: Gui for the LabJack T7(Pro) DAQ board
Home-page: https://gitlab.com/bendub/t7pro
Author: Benoit Dubois
Author-email: benoit.dubois@femto-st.fr
License: UNKNOWN
Platform: UNKNOWN
Classifier: Development Status :: 4 - Beta
Classifier: Environment :: Console
Classifier: Environment :: X11 Applications :: Qt
Classifier: Intended Audience :: End Users/Desktop
Classifier: License :: OSI Approved :: GNU Lesser General Public License v3 or later (LGPLv3+)
Classifier: Natural Language :: English
Classifier: Operating System :: POSIX
Classifier: Topic :: Scientific/Engineering
Requires-Dist: PyQt5
Requires-Dist: benutils
Requires-Dist: labjack
Requires-Dist: numpy
